ai/backend/install/VERSION
ai/backend/install/__init__.py
ai/backend/install/app.py
ai/backend/install/app.tcss
ai/backend/install/cli.py
ai/backend/install/common.py
ai/backend/install/configure.py
ai/backend/install/context.py
ai/backend/install/dev.py
ai/backend/install/docker.py
ai/backend/install/http.py
ai/backend/install/pkg.py
ai/backend/install/py.typed
ai/backend/install/python.py
ai/backend/install/tomltool.py
ai/backend/install/types.py
ai/backend/install/utils.py
ai/backend/install/widgets.py
ai/backend/install/configs/__init__.py
ai/backend/install/configs/agent.toml
ai/backend/install/configs/app-proxy-coordinator.toml
ai/backend/install/configs/app-proxy-worker.toml
ai/backend/install/configs/loki-config.yaml
ai/backend/install/configs/manager.toml
ai/backend/install/configs/otel-collector-config.yaml
ai/backend/install/configs/prometheus.yaml
ai/backend/install/configs/storage-proxy.toml
ai/backend/install/configs/tempo-config.yaml
ai/backend/install/configs/grafana-dashboards/dashboard.json
ai/backend/install/configs/grafana-provisioning/dashboards/dashboards.yaml
ai/backend/install/configs/grafana-provisioning/datasources/datasources.yaml
ai/backend/install/fixtures/__init__.py
ai/backend/install/fixtures/example-container-registries-dockerhub.json
ai/backend/install/fixtures/example-container-registries-harbor.json
ai/backend/install/fixtures/example-keypairs.json
ai/backend/install/fixtures/example-resource-presets.json
ai/backend/install/fixtures/example-roles.json
ai/backend/install/fixtures/example-session-templates.json
ai/backend/install/fixtures/example-set-user-main-access-keys.json
ai/backend/install/fixtures/example-users.json
backend_ai_install-26.1.0.dist-info/METADATA
backend_ai_install-26.1.0.dist-info/WHEEL
backend_ai_install-26.1.0.dist-info/entry_points.txt
backend_ai_install-26.1.0.dist-info/namespace_packages.txt
backend_ai_install-26.1.0.dist-info/top_level.txt
backend_ai_install-26.1.0.dist-info/RECORD
